.testr.conf
AUTHORS
ChangeLog
README.rst
requirements.txt
setup.cfg
setup.py
test-requirements.txt
tox.ini
jenkins_jobs_sauce_ondemand/__init__.py
jenkins_jobs_sauce_ondemand/sauce_ondemand.py
jenkins_jobs_sauce_ondemand.egg-info/PKG-INFO
jenkins_jobs_sauce_ondemand.egg-info/SOURCES.txt
jenkins_jobs_sauce_ondemand.egg-info/dependency_links.txt
jenkins_jobs_sauce_ondemand.egg-info/entry_points.txt
jenkins_jobs_sauce_ondemand.egg-info/not-zip-safe
jenkins_jobs_sauce_ondemand.egg-info/pbr.json
jenkins_jobs_sauce_ondemand.egg-info/requires.txt
jenkins_jobs_sauce_ondemand.egg-info/top_level.txt
tests/__init__.py
tests/base.py
tests/test_saucelabs.py
tests/fixtures/saucelabs001.xml
tests/fixtures/saucelabs001.yaml
tests/fixtures/saucelabs002.xml
tests/fixtures/saucelabs002.yaml