Metadata-Version: 1.1
Name: jenkins-jobs-sauce-ondemand
Version: 0.0.1.dev2
Summary: Jenkins Job Builder plugin for SauceLabs Ondemand
Home-page: https://github.com/zendesk/jenkins-jobs-sauce-ondemand
Author: Russell Sim
Author-email: rsim@zendesk.com
License: Apache License, Version 2.0
Platform: UNKNOWN
Classifier: Topic :: Utilities
Classifier: Environment :: Console
Classifier: Intended Audience :: Developers
Classifier: Intended Audience :: Information Technology
Classifier: Intended Audience :: System Administrators
Classifier: License :: OSI Approved :: Apache Software License
Classifier: Operating System :: OS Independent
Classifier: Programming Language :: Python
Classifier: Programming Language :: Python :: 2
Classifier: Programming Language :: Python :: 2.7
Classifier: Programming Language :: Python :: 3
Classifier: Programming Language :: Python :: 3.4
